{
  "follows": [
    {
      "id": 1372946,
      "login": "amyrlam"
    },
    {
      "id": 54056,
      "login": "bmac"
    },
    {
      "id": 183799,
      "login": "chadhietala"
    },
    {
      "id": 123374,
      "login": "darthdeus"
    },
    {
      "id": 29122,
      "login": "dgeb"
    },
    {
      "id": 1275021,
      "login": "fivetanley"
    },
    {
      "id": 8994,
      "login": "ghempton"
    },
    {
      "id": 17980,
      "login": "hjdivad"
    },
    {
      "id": 16869656,
      "login": "ijlee2"
    },
    {
      "id": 3108309,
      "login": "jasonmit"
    },
    {
      "id": 444218,
      "login": "kategengler"
    },
    {
      "id": 602423,
      "login": "kellyselden"
    },
    {
      "id": 61024,
      "login": "krisselden"
    },
    {
      "id": 594890,
      "login": "mansona"
    },
    {
      "id": 802505,
      "login": "acorncom"
    }
  ]
}